env.py
main.py
meloinf-0.1.0.dist-info/METADATA
meloinf-0.1.0.dist-info/WHEEL
meloinf-0.1.0.dist-info/entry_points.txt
meloinf-0.1.0.dist-info/licenses/LICENSE
utils.py
meloinf-0.1.0.dist-info/RECORD
