Metadata-Version: 2.1
Name: meloinf
Version: 0.1.0
Summary: A cross platform bot base on melobot.
Author-Email: aicorein <aicorein@meloland.org>
License: AGPL3
Requires-Python: >=3.12
Requires-Dist: melobot[onebot]>=3.0.0rc14
Requires-Dist: uvloop>=0.21.0; sys_platform != "win32"
Requires-Dist: pillow>=11.0.0
